anaddb_irreps/__init__.py
anaddb_irreps/abipy_io.py
anaddb_irreps/cli.py
anaddb_irreps/irreps_anaddb.py
anaddb_irreps-0.1.2.dist-info/METADATA
anaddb_irreps-0.1.2.dist-info/WHEEL
anaddb_irreps-0.1.2.dist-info/entry_points.txt
anaddb_irreps-0.1.2.dist-info/top_level.txt
anaddb_irreps-0.1.2.dist-info/RECORD
