Metadata-Version: 2.4
Name: anaddb_irreps
Version: 0.1.2
Summary: anaddb_irreps: use phonopy to find the irreducible representations of the phonon modes from anaddb output. It is a simple wrapper of the Phonopy irreps module.
Author-email: Xu He <mailhexu@gmail.com>
License: BSD-2-clause
Classifier: Development Status :: 3 - Alpha
Classifier: Programming Language :: Python :: 3
Classifier: Operating System :: OS Independent
Classifier: Intended Audience :: Science/Research
Classifier: Topic :: Scientific/Engineering :: Chemistry
Classifier: Topic :: Scientific/Engineering :: Physics
Classifier: License :: OSI Approved :: BSD License
Requires-Python: >=3.6
Requires-Dist: numpy>1.16.5
Requires-Dist: ase>=3.19
Requires-Dist: phonopy>=2.43.0
Requires-Dist: abipy==0.9.8
